ftCLI/__init__.py
ftCLI/ftCLI.py
ftCLI/Lib/Font.py
ftCLI/Lib/VFont.py
ftCLI/Lib/__init__.py
ftCLI/Lib/constants.py
ftCLI/Lib/assistant/__init__.py
ftCLI/Lib/assistant/fonts_data.py
ftCLI/Lib/assistant/styles_mapping.py
ftCLI/Lib/converters/__init__.py
ftCLI/Lib/converters/options.py
ftCLI/Lib/converters/otf_to_ttf.py
ftCLI/Lib/converters/sfnt_to_web.py
ftCLI/Lib/converters/ttc_to_sfnt.py
ftCLI/Lib/converters/ttf_to_otf.py
ftCLI/Lib/converters/variable_to_static.py
ftCLI/Lib/converters/web_to_sfnt.py
ftCLI/Lib/cui/CUI.py
ftCLI/Lib/cui/__init__.py
ftCLI/Lib/misc/__init__.py
ftCLI/Lib/misc/fix_cff_contours.py
ftCLI/Lib/misc/fix_ttf_contours.py
ftCLI/Lib/tables/OS_2.py
ftCLI/Lib/tables/__init__.py
ftCLI/Lib/tables/head.py
ftCLI/Lib/tables/hhea.py
ftCLI/Lib/tables/name.py
ftCLI/Lib/tables/post.py
ftCLI/Lib/utils/__init__.py
ftCLI/Lib/utils/cli_tools.py
ftCLI/Lib/utils/click_tools.py
ftCLI/Lib/utils/glyphs.py
ftCLI/Lib/utils/misc.py
ftCLI/Lib/utils/subsetter.py
ftCLI/commands/__init__.py
ftCLI/commands/ftcli_assistant.py
ftCLI/commands/ftcli_cff.py
ftCLI/commands/ftcli_converter.py
ftCLI/commands/ftcli_fix.py
ftCLI/commands/ftcli_hhea.py
ftCLI/commands/ftcli_metrics.py
ftCLI/commands/ftcli_name.py
ftCLI/commands/ftcli_os2.py
ftCLI/commands/ftcli_post.py
ftCLI/commands/ftcli_print.py
ftCLI/commands/ftcli_utils.py
font_CLI-0.9.20.dist-info/LICENSE
font_CLI-0.9.20.dist-info/METADATA
font_CLI-0.9.20.dist-info/WHEEL
font_CLI-0.9.20.dist-info/entry_points.txt
font_CLI-0.9.20.dist-info/top_level.txt
font_CLI-0.9.20.dist-info/RECORD
