Metadata-Version: 2.1
Name: font-CLI
Version: 0.9.20
Summary: A set of command line tools to edit fonts with FontTools
Home-page: https://github.com/ftCLI/ftCLI
Author: ftCLI
Author-email: ftcli@proton.me
Classifier: Programming Language :: Python :: 3
Classifier: Operating System :: OS Independent
Requires-Python: >=3.8
License-File: LICENSE
Requires-Dist: afdko (>=3.9.6)
Requires-Dist: fonttools (>=4.40.0)
Requires-Dist: beziers (>=0.5.0)
Requires-Dist: brotli (>=1.0.9)
Requires-Dist: click (>=8.1.3)
Requires-Dist: cffsubr (>=0.2.9.post1)
Requires-Dist: dehinter (>=4.0.0)
Requires-Dist: pathvalidate (>=3.0.0)
Requires-Dist: rich (>=13.4.2)
Requires-Dist: skia-pathops (>=0.7.4)
Requires-Dist: ttfautohint-py (>=0.5.1)
Requires-Dist: zopfli (>=0.2.2)
